{"response":{"header":{"resultCode":"00","resultMsg":"NORMAL_SERVICE"},"body":{"dataType":"JSON","items":{"item":[{"baseDate":"20240309","baseTime":"0500","category":"TMP","fcstDate":"20240309","fcstTime":"0600","fcstValue":"-1","nx":61,"ny":126},{"baseDate":"20240309","baseTime":"0500","category":"UUU","fcstDate":"20240309","fcstTime":"0600","fcstValue":"1.3","nx":61,"ny":126},{"baseDate":"20240309","baseTime":"0500","category":"VVV","fcstDate":"20240309","fcstTime":"0600","fcstValue":"-1.1","nx":61,"ny":126},{"baseDate":"20240309","baseTime":"0500","category":"VEC","fcstDate":"20240309","fcstTime":"0600","fcstValue":"310","nx":61,"ny":126},{"baseDate":"20240309","baseTime":"0500","category":"WSD","fcstDate":"20240309","fcstTime":"0600","fcstValue":"1.7","nx":61,"ny":126},{"baseDate":"20240309","baseTime":"0500","category":"SKY","fcstDate":"20240309","fcstTime":"0600","fcstValue":"1","nx":61,"ny":126},{"baseDate":"20240309","baseTime":"0500","category":"PTY","fcstDate":"20240309","fcstTime":"0600","fcstValue":"0","nx":61,"ny":126},{"baseDate":"20240309","baseTime":"0500","category":"POP","fcstDate":"20240309","fcstTime":"0600","fcstValue":"0","nx":61,"ny":126},{"baseDate":"20240309","baseTime":"0500","category":"WAV","fcstDate":"20240309","fcstTime":"0600","fcstValue":"0","nx":61,"ny":126},{"baseDate":"20240309","baseTime":"0500","category":"PCP","fcstDate":"20240309","fcstTime":"0600","fcstValue":"강수없음","nx":61,"ny":126},{"baseDate":"20240309","baseTime":"0500","category":"REH","fcstDate":"20240309","fcstTime":"0600","fcstValue":"60","nx":61,"ny":126},{"baseDate":"20240309","baseTime":"0500","category":"SNO","fcstDate":"20240309","fcstTime":"0600","fcstValue":"적설없음","nx":61,"ny":126},{"baseDate":"20240309","baseTime":"0500","category":"TMP","fcstDate":"20240309","fcstTime":"0700","fcstValue":"-1","nx":61,"ny":126},{"baseDate":"20240309","baseTime":"0500","category":"UUU","fcstDate":"20240309","fcstTime":"0700","fcstValue":"1.3","nx":61,"ny":126},{"baseDate":"20240309","baseTime":"0500","category":"VVV","fcstDate":"20240309","fcstTime":"0700","fcstValue":"-1","nx":61,"ny":126},{"baseDate":"20240309","baseTime":"0500","category":"VEC","fcstDate":"20240309","fcstTime":"0700","fcstValue":"308","nx":61,"ny":126},{"baseDate":"20240309","baseTime":"0500","category":"WSD","fcstDate":"20240309","fcstTime":"0700","fcstValue":"1.6","nx":61,"ny":126},{"baseDate":"20240309","baseTime":"0500","category":"SKY","fcstDate":"20240309","fcstTime":"0700","fcstValue":"1","nx":61,"ny":126},{"baseDate":"20240309","baseTime":"0500","category":"PTY","fcstDate":"20240309","fcstTime":"0700","fcstValue":"0","nx":61,"ny":126},{"baseDate":"20240309","baseTime":"0500","category":"POP","fcstDate":"20240309","fcstTime":"0700","fcstValue":"0","nx":61,"ny":126},{"baseDate":"20240309","baseTime":"0500","category":"WAV","fcstDate":"20240309","fcstTime":"0700","fcstValue":"0","nx":61,"ny":126},{"baseDate":"20240309","baseTime":"0500","category":"PCP","fcstDate":"20240309","fcstTime":"0700","fcstValue":"강수없음","nx":61,"ny":126},{"baseDate":"20240309","baseTime":"0500","category":"REH","fcstDate":"20240309","fcstTime":"0700","fcstValue":"60","nx":61,"ny":126},{"baseDate":"20240309","baseTime":"0500","category":"SNO","fcstDate":"20240309","fcstTime":"0700","fcstValue":"적설없음","nx":61,"ny":126},{"baseDate":"20240309","baseTime":"0500","category":"TMP","fcstDate":"20240309","fcstTime":"0800","fcstValue":"-1","nx":61,"ny":126},{"baseDate":"20240309","baseTime":"0500","category":"UUU","fcstDate":"20240309","fcstTime":"0800","fcstValue":"1.4","nx":61,"ny":126},{"baseDate":"20240309","baseTime":"0500","category":"VVV","fcstDate":"20240309","fcstTime":"0800","fcstValue":"-1.3","nx":61,"ny":126},{"baseDate":"20240309","baseTime":"0500","category":"VEC","fcstDate":"20240309","fcstTime":"0800","fcstValue":"313","nx":61,"ny":126},{"baseDate":"20240309","baseTime":"0500","category":"WSD","fcstDate":"20240309","fcstTime":"0800","fcstValue":"1.9","nx":61,"ny":126},{"baseDate":"20240309","baseTime":"0500","category":"SKY","fcstDate":"20240309","fcstTime":"0800","fcstValue":"1","nx":61,"ny":126},{"baseDate":"20240309","baseTime":"0500","category":"PTY","fcstDate":"20240309","fcstTime":"0800","fcstValue":"0","nx":61,"ny":126},{"baseDate":"20240309","baseTime":"0500","category":"POP","fcstDate":"20240309","fcstTime":"0800","fcstValue":"0","nx":61,"ny":126},{"baseDate":"20240309","baseTime":"0500","category":"WAV","fcstDate":"20240309","fcstTime":"0800","fcstValue":"0","nx":61,"ny":126},{"baseDate":"20240309","baseTime":"0500","category":"PCP","fcstDate":"20240309","fcstTime":"0800","fcstValue":"강수없음","nx":61,"ny":126},{"baseDate":"20240309","baseTime":"0500","category":"REH","fcstDate":"20240309","fcstTime":"0800","fcstValue":"60","nx":61,"ny":126},{"baseDate":"20240309","baseTime":"0500","category":"SNO","fcstDate":"20240309","fcstTime":"0800","fcstValue":"적설없음","nx":61,"ny":126},{"baseDate":"20240309","baseTime":"0500","category":"TMP","fcstDate":"20240309","fcstTime":"0900","fcstValue":"1","nx":61,"ny":126},{"baseDate":"20240309","baseTime":"0500","category":"UUU","fcstDate":"20240309","fcstTime":"0900","fcstValue":"1.6","nx":61,"ny":126},{"baseDate":"20240309","baseTime":"0500","category":"VVV","fcstDate":"20240309","fcstTime":"0900","fcstValue":"-1.2","nx":61,"ny":126},{"baseDate":"20240309","baseTime":"0500","category":"VEC","fcstDate":"20240309","fcstTime":"0900","fcstValue":"307","nx":61,"ny":126},{"baseDate":"20240309","baseTime":"0500","category":"WSD","fcstDate":"20240309","fcstTime":"0900","fcstValue":"2","nx":61,"ny":126},{"baseDate":"20240309","baseTime":"0500","category":"SKY","fcstDate":"20240309","fcstTime":"0900","fcstValue":"1","nx":61,"ny":126},{"baseDate":"20240309","baseTime":"0500","category":"PTY","fcstDate":"20240309","fcstTime":"0900","fcstValue":"0","nx":61,"ny":126},{"baseDate":"20240309","baseTime":"0500","category":"POP","fcstDate":"20240309","fcstTime":"0900","fcstValue":"0","nx":61,"ny":126},{"baseDate":"20240309","baseTime":"0500","category":"WAV","fcstDate":"20240309","fcstTime":"0900","fcstValue":"0","nx":61,"ny":126},{"baseDate":"20240309","baseTime":"0500","category":"PCP","fcstDate":"20240309","fcstTime":"0900","fcstValue":"강수없음","nx":61,"ny":126},{"baseDate":"20240309","baseTime":"0500","category":"REH","fcstDate":"20240309","fcstTime":"0900","fcstValue":"50","nx":61,"ny":126},{"baseDate":"20240309","baseTime":"0500","category":"SNO","fcstDate":"20240309","fcstTime":"0900","fcstValue":"적설없음","nx":61,"ny":126},{"baseDate":"20240309","baseTime":"0500","category":"TMP","fcstDate":"20240309","fcstTime":"1000","fcstValue":"2","nx":61,"ny":126},{"baseDate":"20240309","baseTime":"0500","category":"UUU","fcstDate":"20240309","fcstTime":"1000","fcstValue":"1.8","nx":61,"ny":126},{"baseDate":"20240309","baseTime":"0500","category":"VVV","fcstDate":"20240309","fcstTime":"1000","fcstValue":"-1.3","nx":61,"ny":126},{"baseDate":"20240309","baseTime":"0500","category":"VEC","fcstDate":"20240309","fcstTime":"1000","fcstValue":"306","nx":61,"ny":126},{"baseDate":"20240309","baseTime":"0500","category":"WSD","fcstDate":"20240309","fcstTime":"1000","fcstValue":"2.2","nx":61,"ny":126},{"baseDate":"20240309","baseTime":"0500","category":"SKY","fcstDate":"20240309","fcstTime":"1000","fcstValue":"1","nx":61,"ny":126},{"baseDate":"20240309","baseTime":"0500","category":"PTY","fcstDate":"20240309","fcstTime":"1000","fcstValue":"0","nx":61,"ny":126},{"baseDate":"20240309","baseTime":"0500","category":"POP","fcstDate":"20240309","fcstTime":"1000","fcstValue":"0","nx":61,"ny":126},{"baseDate":"20240309","baseTime":"0500","category":"WAV","fcstDate":"20240309","fcstTime":"1000","fcstValue":"0","nx":61,"ny":126},{"baseDate":"20240309","baseTime":"0500","category":"PCP","fcstDate":"20240309","fcstTime":"1000","fcstValue":"강수없음","nx":61,"ny":126},{"baseDate":"20240309","baseTime":"0500","category":"REH","fcstDate":"20240309","fcstTime":"1000","fcstValue":"45","nx":61,"ny":126},{"baseDate":"20240309","baseTime":"0500","category":"SNO","fcstDate":"20240309","fcstTime":"1000","fcstValue":"적설없음","nx":61,"ny":126},{"baseDate":"20240309","baseTime":"0500","category":"TMP","fcstDate":"20240309","fcstTime":"1100","fcstValue":"4","nx":61,"ny":126},{"baseDate":"20240309","baseTime":"0500","category":"UUU","fcstDate":"20240309","fcstTime":"1100","fcstValue":"1.9","nx":61,"ny":126},{"baseDate":"20240309","baseTime":"0500","category":"VVV","fcstDate":"20240309","fcstTime":"1100","fcstValue":"-1.4","nx":61,"ny":126},{"baseDate":"20240309","baseTime":"0500","category":"VEC","fcstDate":"20240309","fcstTime":"1100","fcstValue":"306","nx":61,"ny":126},{"baseDate":"20240309","baseTime":"0500","category":"WSD","fcstDate":"20240309","fcstTime":"1100","fcstValue":"2.4","nx":61,"ny":126},{"baseDate":"20240309","baseTime":"0500","category":"SKY","fcstDate":"20240309","fcstTime":"1100","fcstValue":"1","nx":61,"ny":126},{"baseDate":"20240309","baseTime":"0500","category":"PTY","fcstDate":"20240309","fcstTime":"1100","fcstValue":"0","nx":61,"ny":126},{"baseDate":"20240309","baseTime":"0500","category":"POP","fcstDate":"20240309","fcstTime":"1100","fcstValue":"0","nx":61,"ny":126},{"baseDate":"20240309","baseTime":"0500","category":"WAV","fcstDate":"20240309","fcstTime":"1100","fcstValue":"0","nx":61,"ny":126},{"baseDate":"20240309","baseTime":"0500","category":"PCP","fcstDate":"20240309","fcstTime":"1100","fcstValue":"강수없음","nx":61,"ny":126},{"baseDate":"20240309","baseTime":"0500","category":"REH","fcstDate":"20240309","fcstTime":"1100","fcstValue":"35","nx":61,"ny":126},{"baseDate":"20240309","baseTime":"0500","category":"SNO","fcstDate":"20240309","fcstTime":"1100","fcstValue":"적설없음","nx":61,"ny":126},{"baseDate":"20240309","baseTime":"0500","category":"TMP","fcstDate":"20240309","fcstTime":"1200","fcstValue":"5","nx":61,"ny":126},{"baseDate":"20240309","baseTime":"0500","category":"UUU","fcstDate":"20240309","fcstTime":"1200","fcstValue":"1.9","nx":61,"ny":126},{"baseDate":"20240309","baseTime":"0500","category":"VVV","fcstDate":"20240309","fcstTime":"1200","fcstValue":"-1.4","nx":61,"ny":126},{"baseDate":"20240309","baseTime":"0500","category":"VEC","fcstDate":"20240309","fcstTime":"1200","fcstValue":"306","nx":61,"ny":126},{"baseDate":"20240309","baseTime":"0500","category":"WSD","fcstDate":"20240309","fcstTime":"1200","fcstValue":"2.4","nx":61,"ny":126},{"baseDate":"20240309","baseTime":"0500","category":"SKY","fcstDate":"20240309","fcstTime":"1200","fcstValue":"1","nx":61,"ny":126},{"baseDate":"20240309","baseTime":"0500","category":"PTY","fcstDate":"20240309","fcstTime":"1200","fcstValue":"0","nx":61,"ny":126},{"baseDate":"20240309","baseTime":"0500","category":"POP","fcstDate":"20240309","fcstTime":"1200","fcstValue":"0","nx":61,"ny":126},{"baseDate":"20240309","baseTime":"0500","category":"WAV","fcstDate":"20240309","fcstTime":"1200","fcstValue":"0","nx":61,"ny":126},{"baseDate":"20240309","baseTime":"0500","category":"PCP","fcstDate":"20240309","fcstTime":"1200","fcstValue":"강수없음","nx":61,"ny":126},{"baseDate":"20240309","baseTime":"0500","category":"REH","fcstDate":"20240309","fcstTime":"1200","fcstValue":"30","nx":61,"ny":126},{"baseDate":"20240309","baseTime":"0500","category":"SNO","fcstDate":"20240309","fcstTime":"1200","fcstValue":"적설없음","nx":61,"ny":126},{"baseDate":"20240309","baseTime":"0500","category":"TMP","fcstDate":"20240309","fcstTime":"1300","fcstValue":"5","nx":61,"ny":126},{"baseDate":"20240309","baseTime":"0500","category":"UUU","fcstDate":"20240309","fcstTime":"1300","fcstValue":"1.9","nx":61,"ny":126},{"baseDate":"20240309","baseTime":"0500","category":"VVV","fcstDate":"20240309","fcstTime":"1300","fcstValue":"-1.4","nx":61,"ny":126},{"baseDate":"20240309","baseTime":"0500","category":"VEC","fcstDate":"20240309","fcstTime":"1300","fcstValue":"306","nx":61,"ny":126},{"baseDate":"20240309","baseTime":"0500","category":"WSD","fcstDate":"20240309","fcstTime":"1300","fcstValue":"2.4","nx":61,"ny":126},{"baseDate":"20240309","baseTime":"0500","category":"SKY","fcstDate":"20240309","fcstTime":"1300","fcstValue":"1","nx":61,"ny":126},{"baseDate":"20240309","baseTime":"0500","category":"PTY","fcstDate":"20240309","fcstTime":"1300","fcstValue":"0","nx":61,"ny":126},{"baseDate":"20240309","baseTime":"0500","category":"POP","fcstDate":"20240309","fcstTime":"1300","fcstValue":"0","nx":61,"ny":126},{"baseDate":"20240309","baseTime":"0500","category":"WAV","fcstDate":"20240309","fcstTime":"1300","fcstValue":"0","nx":61,"ny":126},{"baseDate":"20240309","baseTime":"0500","category":"PCP","fcstDate":"20240309","fcstTime":"1300","fcstValue":"강수없음","nx":61,"ny":126},{"baseDate":"20240309","baseTime":"0500","category":"REH","fcstDate":"20240309","fcstTime":"1300","fcstValue":"30","nx":61,"ny":126},{"baseDate":"20240309","baseTime":"0500","category":"SNO","fcstDate":"20240309","fcstTime":"1300","fcstValue":"적설없음","nx":61,"ny":126},{"baseDate":"20240309","baseTime":"0500","category":"TMP","fcstDate":"20240309","fcstTime":"1400","fcstValue":"6","nx":61,"ny":126},{"baseDate":"20240309","baseTime":"0500","category":"UUU","fcstDate":"20240309","fcstTime":"1400","fcstValue":"2","nx":61,"ny":126},{"baseDate":"20240309","baseTime":"0500","category":"VVV","fcstDate":"20240309","fcstTime":"1400","fcstValue":"-1.3","nx":61,"ny":126},{"baseDate":"20240309","baseTime":"0500","category":"VEC","fcstDate":"20240309","fcstTime":"1400","fcstValue":"303","nx":61,"ny":126},{"baseDate":"20240309","baseTime":"0500","category":"WSD","fcstDate":"20240309","fcstTime":"1400","fcstValue":"2.4","nx":61,"ny":126},{"baseDate":"20240309","baseTime":"0500","category":"SKY","fcstDate":"20240309","fcstTime":"1400","fcstValue":"1","nx":61,"ny":126},{"baseDate":"20240309","baseTime":"0500","category":"PTY","fcstDate":"20240309","fcstTime":"1400","fcstValue":"0","nx":61,"ny":126},{"baseDate":"20240309","baseTime":"0500","category":"POP","fcstDate":"20240309","fcstTime":"1400","fcstValue":"0","nx":61,"ny":126},{"baseDate":"20240309","baseTime":"0500","category":"WAV","fcstDate":"20240309","fcstTime":"1400","fcstValue":"0","nx":61,"ny":126},{"baseDate":"20240309","baseTime":"0500","category":"PCP","fcstDate":"20240309","fcstTime":"1400","fcstValue":"강수없음","nx":61,"ny":126},{"baseDate":"20240309","baseTime":"0500","category":"REH","fcstDate":"20240309","fcstTime":"1400","fcstValue":"25","nx":61,"ny":126},{"baseDate":"20240309","baseTime":"0500","category":"SNO","fcstDate":"20240309","fcstTime":"1400","fcstValue":"적설없음","nx":61,"ny":126},{"baseDate":"20240309","baseTime":"0500","category":"TMP","fcstDate":"20240309","fcstTime":"1500","fcstValue":"7","nx":61,"ny":126},{"baseDate":"20240309","baseTime":"0500","category":"UUU","fcstDate":"20240309","fcstTime":"1500","fcstValue":"2.2","nx":61,"ny":126},{"baseDate":"20240309","baseTime":"0500","category":"VVV","fcstDate":"20240309","fcstTime":"1500","fcstValue":"-1.1","nx":61,"ny":126},{"baseDate":"20240309","baseTime":"0500","category":"VEC","fcstDate":"20240309","fcstTime":"1500","fcstValue":"297","nx":61,"ny":126},{"baseDate":"20240309","baseTime":"0500","category":"WSD","fcstDate":"20240309","fcstTime":"1500","fcstValue":"2.5","nx":61,"ny":126},{"baseDate":"20240309","baseTime":"0500","category":"SKY","fcstDate":"20240309","fcstTime":"1500","fcstValue":"1","nx":61,"ny":126},{"baseDate":"20240309","baseTime":"0500","category":"PTY","fcstDate":"20240309","fcstTime":"1500","fcstValue":"0","nx":61,"ny":126},{"baseDate":"20240309","baseTime":"0500","category":"POP","fcstDate":"20240309","fcstTime":"1500","fcstValue":"0","nx":61,"ny":126},{"baseDate":"20240309","baseTime":"0500","category":"WAV","fcstDate":"20240309","fcstTime":"1500","fcstValue":"0","nx":61,"ny":126},{"baseDate":"20240309","baseTime":"0500","category":"PCP","fcstDate":"20240309","fcstTime":"1500","fcstValue":"강수없음","nx":61,"ny":126},{"baseDate":"20240309","baseTime":"0500","category":"REH","fcstDate":"20240309","fcstTime":"1500","fcstValue":"25","nx":61,"ny":126},{"baseDate":"20240309","baseTime":"0500","category":"SNO","fcstDate":"20240309","fcstTime":"1500","fcstValue":"적설없음","nx":61,"ny":126},{"baseDate":"20240309","baseTime":"0500","category":"TMX","fcstDate":"20240309","fcstTime":"1500","fcstValue":"7.0","nx":61,"ny":126},{"baseDate":"20240309","baseTime":"0500","category":"TMP","fcstDate":"20240309","fcstTime":"1600","fcstValue":"7","nx":61,"ny":126},{"baseDate":"20240309","baseTime":"0500","category":"UUU","fcstDate":"20240309","fcstTime":"1600","fcstValue":"2.2","nx":61,"ny":126},{"baseDate":"20240309","baseTime":"0500","category":"VVV","fcstDate":"20240309","fcstTime":"1600","fcstValue":"-0.8","nx":61,"ny":126},{"baseDate":"20240309","baseTime":"0500","category":"VEC","fcstDate":"20240309","fcstTime":"1600","fcstValue":"290","nx":61,"ny":126},{"baseDate":"20240309","baseTime":"0500","category":"WSD","fcstDate":"20240309","fcstTime":"1600","fcstValue":"2.3","nx":61,"ny":126},{"baseDate":"20240309","baseTime":"0500","category":"SKY","fcstDate":"20240309","fcstTime":"1600","fcstValue":"1","nx":61,"ny":126},{"baseDate":"20240309","baseTime":"0500","category":"PTY","fcstDate":"20240309","fcstTime":"1600","fcstValue":"0","nx":61,"ny":126},{"baseDate":"20240309","baseTime":"0500","category":"POP","fcstDate":"20240309","fcstTime":"1600","fcstValue":"0","nx":61,"ny":126},{"baseDate":"20240309","baseTime":"0500","category":"WAV","fcstDate":"20240309","fcstTime":"1600","fcstValue":"0","nx":61,"ny":126},{"baseDate":"20240309","baseTime":"0500","category":"PCP","fcstDate":"20240309","fcstTime":"1600","fcstValue":"강수없음","nx":61,"ny":126},{"baseDate":"20240309","baseTime":"0500","category":"REH","fcstDate":"20240309","fcstTime":"1600","fcstValue":"25","nx":61,"ny":126},{"baseDate":"20240309","baseTime":"0500","category":"SNO","fcstDate":"20240309","fcstTime":"1600","fcstValue":"적설없음","nx":61,"ny":126},{"baseDate":"20240309","baseTime":"0500","category":"TMP","fcstDate":"20240309","fcstTime":"1700","fcstValue":"7","nx":61,"ny":126},{"baseDate":"20240309","baseTime":"0500","category":"UUU","fcstDate":"20240309","fcstTime":"1700","fcstValue":"2.1","nx":61,"ny":126},{"baseDate":"20240309","baseTime":"0500","category":"VVV","fcstDate":"20240309","fcstTime":"1700","fcstValue":"-0.2","nx":61,"ny":126},{"baseDate":"20240309","baseTime":"0500","category":"VEC","fcstDate":"20240309","fcstTime":"1700","fcstValue":"275","nx":61,"ny":126},{"baseDate":"20240309","baseTime":"0500","category":"WSD","fcstDate":"20240309","fcstTime":"1700","fcstValue":"2.1","nx":61,"ny":126},{"baseDate":"20240309","baseTime":"0500","category":"SKY","fcstDate":"20240309","fcstTime":"1700","fcstValue":"1","nx":61,"ny":126},{"baseDate":"20240309","baseTime":"0500","category":"PTY","fcstDate":"20240309","fcstTime":"1700","fcstValue":"0","nx":61,"ny":126},{"baseDate":"20240309","baseTime":"0500","category":"POP","fcstDate":"20240309","fcstTime":"1700","fcstValue":"0","nx":61,"ny":126},{"baseDate":"20240309","baseTime":"0500","category":"WAV","fcstDate":"20240309","fcstTime":"1700","fcstValue":"0","nx":61,"ny":126},{"baseDate":"20240309","baseTime":"0500","category":"PCP","fcstDate":"20240309","fcstTime":"1700","fcstValue":"강수없음","nx":61,"ny":126},{"baseDate":"20240309","baseTime":"0500","category":"REH","fcstDate":"20240309","fcstTime":"1700","fcstValue":"30","nx":61,"ny":126}]},"pageNo":1,"numOfRows":144,"totalCount":809}}}